AhmadYasin/ANN_Lab.py
AhmadYasin/AhmadYasin.py
AhmadYasin/ML_Lab.py
AhmadYasin/__init__.py
AhmadYasin-1.1.1.dist-info/LICENSE
AhmadYasin-1.1.1.dist-info/METADATA
AhmadYasin-1.1.1.dist-info/WHEEL
AhmadYasin-1.1.1.dist-info/top_level.txt
AhmadYasin-1.1.1.dist-info/RECORD
