Metadata-Version: 2.2
Name: AhmadYasin
Version: 1.1.1
Summary: A helper library with useful functions.
Home-page: https://github.com/AhmadYasin1
Author: Ahmad Yasin
Author-email: ahmadyasin.info@gmail.com
Classifier: Programming Language :: Python :: 3
Classifier: License :: OSI Approved :: MIT License
Classifier: Operating System :: OS Independent
Requires-Python: >=3.6
License-File: LICENSE
Dynamic: author
Dynamic: author-email
Dynamic: classifier
Dynamic: description
Dynamic: description-content-type
Dynamic: home-page
Dynamic: requires-python
Dynamic: summary
